surgen/__init__.py
surgen/exceptions.py
surgen/log.py
surgen/main.py
surgen/procedure.py
surgen/results.py
surgen/surgen.py
surgen/target/__init__.py
surgen/target/base.py
surgen/target/git_target.py
surgen/target/local_target.py
surgen/tests/__init__.py
surgen/tests/test_procedure.py
surgen/tests/test_result_set.py
surgen/tests/test_surgen.py
surgen/tests/utils.py
surgen/utils/__init__.py
surgen/utils/file.py
surgen/utils/string.py
surgen/utils/testing.py
surgen-0.1.0.dist-info/LICENSE
surgen-0.1.0.dist-info/METADATA
surgen-0.1.0.dist-info/WHEEL
surgen-0.1.0.dist-info/entry_points.txt
surgen-0.1.0.dist-info/top_level.txt
surgen-0.1.0.dist-info/RECORD
