Metadata-Version: 2.1
Name: surgen
Version: 0.1.0
Summary: a utility library to help provide api route generation form function signature for web frameworks.
Home-page: https://github.com/toumorokoshi/surgen
Author: Yusuke Tsutsumi
Author-email: yusuke@tsutsumi.io
License: UNKNOWN
Platform: UNKNOWN
Classifier: Development Status :: 5 - Production/Stable
Classifier: Operating System :: MacOS
Classifier: Operating System :: POSIX :: Linux
Classifier: Topic :: System :: Software Distribution
Classifier: License :: OSI Approved :: MIT License
Classifier: Programming Language :: Python
Classifier: Programming Language :: Python :: 3
Requires-Dist: attrs
Requires-Dist: clint
Requires-Dist: coloredlogs
Requires-Dist: docopt
Requires-Dist: gitpython
Requires-Dist: py
Requires-Dist: verboselogs
